pyrman/__init__.py
pyrman/__main__.py
pyrman/client.py
pyrman/context.py
pyrman/models.py
pyrman/serialize.py
pyrman/setupmeta.py
pyrman/pypi/__init__.py
pyrman/pypi/client.py
pyrman/pypi/parsers.py
pyrman/pypi/session.py
releases_manager-0.0.6.dist-info/METADATA
releases_manager-0.0.6.dist-info/WHEEL
releases_manager-0.0.6.dist-info/entry_points.txt
releases_manager-0.0.6.dist-info/top_level.txt
releases_manager-0.0.6.dist-info/RECORD
