Metadata-Version: 2.1
Name: releases-manager
Version: 0.0.6
Summary: Manage python published release for packages that you owns on PyPI.
Home-page: UNKNOWN
License: UNKNOWN
Platform: UNKNOWN
Requires-Dist: bs4
Requires-Dist: click
Requires-Dist: pydantic
Requires-Dist: pyyaml
Requires-Dist: requests
